LICENSE
MANIFEST.in
README.md
setup.cfg
setup.py
sfrtv.conf
sfrtvctl/__init__.py
sfrtvctl/__main__.py
sfrtvctl/exceptions.py
sfrtvctl/interactive.py
sfrtvctl/remote.py
sfrtvctl.egg-info/PKG-INFO
sfrtvctl.egg-info/SOURCES.txt
sfrtvctl.egg-info/dependency_links.txt
sfrtvctl.egg-info/entry_points.txt
sfrtvctl.egg-info/requires.txt
sfrtvctl.egg-info/top_level.txt