Metadata-Version: 1.1
Name: sfrtvctl
Version: 0.1.2
Summary: Remote control SFR TV Power via TCP/IP connection
Home-page: https://github.com/dragouf/sfrtvctl
Author: David LAURENT
Author-email: dragouf@hotmail.fr
License: MIT
Platform: UNKNOWN
Classifier: Development Status :: 4 - Beta
Classifier: Environment :: Console
Classifier: License :: OSI Approved :: MIT License
Classifier: Programming Language :: Python :: 3
Classifier: Topic :: Home Automation
